ffhq_align/__init__.py
ffhq_align/__version__.py
ffhq_align/module.py
ffhq_align/ops.py
ffhq_align/utils.py
ffhq_align-1.0.4.dist-info/LICENSE.md
ffhq_align-1.0.4.dist-info/METADATA
ffhq_align-1.0.4.dist-info/WHEEL
ffhq_align-1.0.4.dist-info/top_level.txt
ffhq_align-1.0.4.dist-info/RECORD
